gqylpy.py
gqylpy-1.0.dist-info/LICENSE
gqylpy-1.0.dist-info/METADATA
gqylpy-1.0.dist-info/WHEEL
gqylpy-1.0.dist-info/top_level.txt
gqylpy-1.0.dist-info/RECORD
