Metadata-Version: 2.1
Name: gqylpy
Version: 1.0
Summary: The GQYLPY.
Home-page: http://gqylpy.com
Author: 竹永康
Author-email: <gqylpy@outlook.com>
License: Apache 2.0
Project-URL: Source, https://github.com/gqylpy/gqylpy
Platform: UNKNOWN
Classifier: License :: OSI Approved :: Apache Software License
License-File: LICENSE
